mavsniff/__init__.py
mavsniff/__main__.py
mavsniff/capture.py
mavsniff/commands/__init__.py
mavsniff/commands/capture.py
mavsniff/commands/ports.py
mavsniff/commands/replay.py
mavsniff/commands/wsplugin.py
mavsniff/replay.py
mavsniff/utils/__init__.py
mavsniff/utils/ip.py
mavsniff/utils/log.py
mavsniff/utils/mav.py
mavsniff-1.0.0.dist-info/METADATA
mavsniff-1.0.0.dist-info/WHEEL
mavsniff-1.0.0.dist-info/entry_points.txt
mavsniff-1.0.0.dist-info/RECORD
