Metadata-Version: 2.1
Name: mavsniff
Version: 1.0.0
Summary: Mavsniff enables you to capture and replay MAVLink communication over serial line or network
Home-page: https://github.com/dronetag/mavsniff
License: MIT
Author: Tomas Peterka
Author-email: tomas.peterka@dronetag.cz
Requires-Python: >=3.8,<4.0
Classifier: License :: OSI Approved :: MIT License
Classifier: Operating System :: OS Independent
Classifier: Programming Language :: Python :: 3
Classifier: Programming Language :: Python :: 3.8
Classifier: Programming Language :: Python :: 3.9
Classifier: Programming Language :: Python :: 3.10
Classifier: Programming Language :: Python :: 3.11
Classifier: Programming Language :: Python :: 3.12
Provides-Extra: dev
Requires-Dist: click
Requires-Dist: mypy ; extra == "dev"
Requires-Dist: pre-commit ; extra == "dev"
Requires-Dist: pymavlink (>=2.4.20,<3.0.0)
Requires-Dist: pyserial (>=3.5,<4.0)
Requires-Dist: pytest ; extra == "dev"
Requires-Dist: pytest-cov ; extra == "dev"
Requires-Dist: python-pcapng (>=2.1.1,<3.0.0)
Requires-Dist: ruff ; extra == "dev"
Requires-Dist: wheel ; extra == "dev"
Project-URL: Repository, https://github.com/dronetag/mavsniff
